master_dac/__init__.py
master_dac/__main__.py
master_dac/configuration.py
master_dac/datasets.py
master_dac/install.py
master_dac/requirements/amal.txt
master_dac/requirements/deep.txt
master_dac/requirements/rital.txt
master_dac/requirements/rld.txt
master_dac/rld/__init__.py
master_dac/rld/stk.py
master_dac/utils.py
master_dac-2025.9.21.dist-info/METADATA
master_dac-2025.9.21.dist-info/WHEEL
master_dac-2025.9.21.dist-info/entry_points.txt
master_dac-2025.9.21.dist-info/RECORD
