Metadata-Version: 2.3
Name: master_dac
Version: 2025.9.21
Summary: Master DAC dependency & dataset manager
Author: Benjamin Piwowarski
Author-email: benjamin@piwowarski.fr
Classifier: Programming Language :: Python :: 2
Classifier: Programming Language :: Python :: 2.7
Classifier: Programming Language :: Python :: 3
Classifier: Programming Language :: Python :: 3.4
Classifier: Programming Language :: Python :: 3.5
Classifier: Programming Language :: Python :: 3.6
Classifier: Programming Language :: Python :: 3.7
Classifier: Programming Language :: Python :: 3.8
Classifier: Programming Language :: Python :: 3.9
Classifier: Programming Language :: Python :: 3.10
Classifier: Programming Language :: Python :: 3.11
Classifier: Programming Language :: Python :: 3.12
Classifier: Programming Language :: Python :: 3.13
Requires-Dist: appdirs (>=1.4,<2.0)
Requires-Dist: cached-property (>=1.5,<2.0) ; python_version <= "3.7"
Requires-Dist: click (>=8,<9)
Requires-Dist: easypip (>=1.3.4,<2.0.0)
Requires-Dist: importlib_resources (>=6,<7) ; python_version <= "3.8"
Requires-Dist: packaging (>=23,<24)
Requires-Dist: requests (>=2,<3)
